Workbook

Sheet About
E1: Declaration of AI Assistance: All data modeling, functions, and analytical logic within these Excel projects were developed independently. Generative AI tools (ChatGPT and Gemini) were utilized solely to enhance syntax, tone, and readability of textual elements.
B2: Construction Project Monitoring Dashboard
B3: A single-project cost, billing and progress dashboard for a construction project at 75% completion.
B5: ⚠ ILLUSTRATIVE / SAMPLE DATA — built to demonstrate methodology. Project 'Skyline Terraces — Block C', all names and figures are fictional and do not represent any real company or client.
B7: WHAT THIS SHOWS
B8: • Live KPI tiles: total budget (₹16 Cr), amount spent, % utilised, completion %, cost variance, estimate at completion, and RA billing position.
B9: • Cost breakdown by category (material, labour, subcontractor, equipment, overheads) with a donut chart and cost-to-complete.
B10: • RA Bill status — running-account bills raised to the client: gross value, certified, 5% retention, received and pending.
B11: • Subcontractor tracker — order value, billed, paid and balance by work package.
B12: • Project-specific manpower and work-time costing (headcount × days × rate).
B13: • Material consumption (budget vs actual quantity) and Purchase Price Variance for cement and steel.
B14: • Milestone/schedule tracker (planned vs actual %) and a monthly cash-flow view (inflow vs outflow, cumulative).
B15: • Every figure is formula-driven across seven data tabs — change an input and the dashboard updates.
... B20: Built by Akhila Nayak · Accountant · R2R, MIS & Cost Analysis

Sheet Dashboard
B2: Construction Project Monitoring Dashboard
B3: Skyline Terraces — Block C · 75% Complete · ₹16 Cr Estimate · Illustrative data (INR)
B5: TOTAL BUDGET | E5: AMOUNT SPENT | H5: % UTILISED | K5: COMPLETION
B6: =Project_Data!C6 -> 160000000 | E6: =Project_Data!D20 -> 122600000 | H6: =Project_Data!D20/Project_Data!C6 -> 0.76625 | K6: =Project_Data!C7 -> 0.75
B9: COST VAR (EV−AC) | E9: CPI | H9: EAC (BAC/CPI) | K9: RA RECEIVED
B10: =Project_Data!C29 -> -2600000 | E10: =Project_Data!C30 -> 0.97879282 | H10: =Project_Data!C31 -> 1.6346667e+08 | K10: =RA_Bills!G15 -> 114100000
B14: COST BREAKDOWN BY CATEGORY | F14: RA BILL SUMMARY | I14: EARNED VALUE (EVM)
B15: Category | C15: Actual (₹)
B16: Material | C16: =Project_Data!D15 -> 50200000 | F16: Gross Work Value | G16: =RA_Bills!D15 -> 131500000 | I16: BAC — Budget | K16: =Project_Data!C25 -> 160000000
B17: Labour | C17: =Project_Data!D16 -> 30800000 | F17: Amount Certified | G17: =RA_Bills!E15 -> 128600000 | I17: EV — Earned Value | K17: =Project_Data!C27 -> 120000000
B18: Subcontractor | C18: =Project_Data!D17 -> 23100000 | F18: Retention Held | G18: =RA_Bills!F15 -> 6430000 | I18: AC — Actual Cost | K18: =Project_Data!C28 -> 122600000
B19: Equipment | C19: =Project_Data!D18 -> 10600000 | F19: Amount Received | G19: =RA_Bills!G15 -> 114100000 | I19: CPI | K19: =Project_Data!C30 -> 0.97879282
B20: Overheads | C20: =Project_Data!D19 -> 7900000 | F20: Pending Receivable | G20: =RA_Bills!H15 -> 8070000 | I20: VAC — Var at Completion | K20: =Project_Data!C32 -> -3466666.7

Sheet Project_Data
B2: Project Master Data
B4: Project Name | C4: Skyline Terraces — Block C
B5: Project Type | C5: Construction (Residential/Commercial)
B6: Total Estimated Cost (Budget) | C6: 160000000
B7: Overall Completion % | C7: 0.75
B8: Planned Completion % (as per schedule) | C8: 0.8
B9: Project Start | C9: Apr 2024
B10: Scheduled Completion | C10: Mar 2026
B13: Cost by Category
B14: Category | C14: Budget (₹) | D14: Actual to Date (₹) | E14: % of Budget Spent | F14: Cost to Complete (₹)
B15: Material | C15: 64000000 | D15: 50200000 | E15: =IFERROR(D15/C15,0) -> 0.784375 | F15: =C15-D15 -> 13800000
B16: Labour | C16: 40000000 | D16: 30800000 | E16: =IFERROR(D16/C16,0) -> 0.77 | F16: =C16-D16 -> 9200000
B17: Subcontractor | C17: 32000000 | D17: 23100000 | E17: =IFERROR(D17/C17,0) -> 0.721875 | F17: =C17-D17 -> 8900000
B18: Equipment | C18: 14000000 | D18: 10600000 | E18: =IFERROR(D18/C18,0) -> 0.75714286 | F18: =C18-D18 -> 3400000
B19: Overheads | C19: 10000000 | D19: 7900000 | E19: =IFERROR(D19/C19,0) -> 0.79 | F19: =C19-D19 -> 2100000
B20: TOTAL | C20: =SUM(C15:C19) -> 160000000 | D20: =SUM(D15:D19) -> 122600000 | E20: =IFERROR(D20/C20,0) -> 0.76625 | F20: =SUM(F15:F19) -> 37400000
B23: Earned Value Analysis (EVM)
B24: Standard project-controls metrics. EV = BAC × % complete; CPI = EV / AC; EAC = BAC / CPI.
B25: BAC — Budget at Completion | C25: =C6 -> 160000000 | D25: Total project budget
B26: % Complete (physical) | C26: =C7 -> 0.75 | D26: Work actually done
B27: EV — Earned Value | C27: =C6*C7 -> 120000000 | D27: Budgeted cost of work performed
B28: AC — Actual Cost | C28: =D20 -> 122600000 | D28: Actual cost incurred to date
B29: CV — Cost Variance (EV − AC) | C29: =C27-C28 -> -2600000 | D29: Positive = under budget
B30: CPI — Cost Performance Index | C30: =IFERROR(C27/C28,0) -> 0.97879282 | D30: EV / AC; >1 = efficient
B31: EAC — Estimate at Completion | C31: =IFERROR(C25/C30,0) -> 1.6346667e+08 | D31: BAC / CPI
B32: VAC — Variance at Completion | C32: =C25-C31 -> -3466666.7 | D32: BAC − EAC

Sheet RA_Bills
B2: Running Account (RA) Bill Status
B3: Bills raised to client — certified, retention, received, pending.
B5: RA Bill No. | C5: Date | D5: Gross Work Value (₹) | E5: Amount Certified (₹) | F5: Retention @5% (₹) | G5: Amount Received (₹) | H5: Pending Receivable (₹) | I5: Excess Received (₹)
B6: RA-01 | C6: May-24 | D6: 12500000 | E6: 12200000 | F6: =E6*0.05 -> 610000 | G6: 11200000 | H6: =MAX(E6-F6-G6,0) -> 390000 | I6: =MAX(G6-(E6-F6),0) -> 0
B7: RA-02 | C7: Jul-24 | D7: 14800000 | E7: 14500000 | F7: =E7*0.05 -> 725000 | G7: 13400000 | H7: =MAX(E7-F7-G7,0) -> 375000 | I7: =MAX(G7-(E7-F7),0) -> 0
B8: RA-03 | C8: Sep-24 | D8: 16200000 | E8: 15900000 | F8: =E8*0.05 -> 795000 | G8: 14600000 | H8: =MAX(E8-F8-G8,0) -> 505000 | I8: =MAX(G8-(E8-F8),0) -> 0
B9: RA-04 | C9: Nov-24 | D9: 15100000 | E9: 14800000 | F9: =E9*0.05 -> 740000 | G9: 13600000 | H9: =MAX(E9-F9-G9,0) -> 460000 | I9: =MAX(G9-(E9-F9),0) -> 0
B10: RA-05 | C10: Jan-25 | D10: 17400000 | E10: 17000000 | F10: =E10*0.05 -> 850000 | G10: 15700000 | H10: =MAX(E10-F10-G10,0) -> 450000 | I10: =MAX(G10-(E10-F10),0) -> 0
B11: RA-06 | C11: Mar-25 | D11: 13900000 | E11: 13600000 | F11: =E11*0.05 -> 680000 | G11: 12300000 | H11: =MAX(E11-F11-G11,0) -> 620000 | I11: =MAX(G11-(E11-F11),0) -> 0
B12: RA-07 | C12: May-25 | D12: 15600000 | E12: 15200000 | F12: =E12*0.05 -> 760000 | G12: 13900000 | H12: =MAX(E12-F12-G12,0) -> 540000 | I12: =MAX(G12-(E12-F12),0) -> 0
B13: RA-08 | C13: Jul-25 | D13: 14200000 | E13: 13900000 | F13: =E13*0.05 -> 695000 | G13: 11800000 | H13: =MAX(E13-F13-G13,0) -> 1405000 | I13: =MAX(G13-(E13-F13),0) -> 0
B14: RA-09 | C14: Sep-25 | D14: 11800000 | E14: 11500000 | F14: =E14*0.05 -> 575000 | G14: 7600000 | H14: =MAX(E14-F14-G14,0) -> 3325000 | I14: =MAX(G14-(E14-F14),0) -> 0
B15: TOTAL | D15: =SUM(D6:D14) -> 131500000 | E15: =SUM(E6:E14) -> 128600000 | F15: =SUM(F6:F14) -> 6430000 | G15: =SUM(G6:G14) -> 114100000 | H15: =SUM(H6:H14) -> 8070000 | I15: =SUM(I6:I14) -> 0

Sheet Subcontractors
B2: Subcontractor Status
B4: Subcontractor | C4: Work Package | D4: Order Value (₹) | E4: Billed to Date (₹) | F4: Paid (₹) | G4: Balance Payable (₹) | H4: % Billed
B5: Sri Sai Enterprises | C5: Piling & Foundation | D5: 8500000 | E5: 8500000 | F5: 8100000 | G5: =E5-F5 -> 400000 | H5: =IFERROR(E5/D5,0) -> 1
B6: Deccan Steel Works | C6: Structural Steel | D6: 9200000 | E6: 7400000 | F6: 6900000 | G6: =E6-F6 -> 500000 | H6: =IFERROR(E6/D6,0) -> 0.80434783
B7: Kaveri Electricals | C7: Electrical & Wiring | D7: 4800000 | E7: 3100000 | F7: 2700000 | G7: =E7-F7 -> 400000 | H7: =IFERROR(E7/D7,0) -> 0.64583333
B8: Nandi Plumbing Co. | C8: Plumbing & Sanitary | D8: 3600000 | E8: 2500000 | F8: 2200000 | G8: =E8-F8 -> 300000 | H8: =IFERROR(E8/D8,0) -> 0.69444444
B9: Prism Interiors | C9: Finishing & Interiors | D9: 5900000 | E9: 1600000 | F9: 1300000 | G9: =E9-F9 -> 300000 | H9: =IFERROR(E9/D9,0) -> 0.27118644
B10: TOTAL | D10: =SUM(D5:D9) -> 32000000 | E10: =SUM(E5:E9) -> 23100000 | F10: =SUM(F5:F9) -> 21200000 | G10: =SUM(G5:G9) -> 1900000 | H10: =IFERROR(E10/D10,0) -> 0.721875

Sheet Manpower
B2: Project-Specific Manpower & Work-Time Costing
B3: Direct site labour (headcount × days × rate) plus agency/contract labour. Ties to Labour actual in Project_Data.
B5: Role / Trade | C5: Headcount | D5: Days Deployed | E5: Rate (₹/day) | F5: Labour Cost (₹)
B6: Project Manager | C6: 1 | D6: 540 | E6: 4500 | F6: =C6*D6*E6 -> 2430000
B7: Site Engineers | C7: 3 | D7: 520 | E7: 2600 | F7: =C7*D7*E7 -> 4056000
B8: Supervisors | C8: 4 | D8: 510 | E8: 1800 | F8: =C8*D8*E8 -> 3672000
B9: Masons | C9: 13 | D9: 405 | E9: 850 | F9: =C9*D9*E9 -> 4475250
B10: Bar Benders / Steel Fixers | C10: 8 | D10: 395 | E10: 900 | F10: =C10*D10*E10 -> 2844000
B11: Carpenters / Shuttering | C11: 10 | D11: 390 | E11: 880 | F11: =C11*D11*E11 -> 3432000
B12: Electricians | C12: 5 | D12: 265 | E12: 950 | F12: =C12*D12*E12 -> 1258750
B13: Plumbers | C13: 4 | D13: 245 | E13: 920 | F13: =C13*D13*E13 -> 901600
B14: Helpers / Unskilled | C14: 28 | D14: 410 | E14: 520 | F14: =C14*D14*E14 -> 5969600
B15: Agency / Contract Labour | F15: 1760800
B16: TOTAL LABOUR | C16: =SUM(C6:C14) -> 76 | F16: =SUM(F6:F15) -> 30800000
B18: Reconciliation Check
B19: Labour actual (Project_Data) | F19: =Project_Data!D16 -> 30800000
B20: Total labour (this sheet) | F20: =F16 -> 30800000
B21: Difference | F21: =F19-F20 -> 0

Sheet Materials
B2: Material Consumption & Purchase Price Variance
B4: Material Consumption (Budget Qty vs Actual)
B5: Material | C5: Unit | D5: Budget Qty | E5: Actual Qty (to date) | F5: Qty Variance | G5: Status
B6: Cement | C6: Bags | D6: 42000 | E6: 33200 | F6: =D6-E6 -> 8800 | G6: =IF(E6<=D6,"Within Budget","Over Budget") -> Within Budget
B7: Steel (TMT) | C7: MT | D7: 1350 | E7: 1058 | F7: =D7-E7 -> 292 | G7: =IF(E7<=D7,"Within Budget","Over Budget") -> Within Budget
B8: Sand | C8: CFT | D8: 210000 | E8: 168500 | F8: =D8-E8 -> 41500 | G8: =IF(E8<=D8,"Within Budget","Over Budget") -> Within Budget
B9: Aggregate (20mm) | C9: CFT | D9: 185000 | E9: 146200 | F9: =D9-E9 -> 38800 | G9: =IF(E9<=D9,"Within Budget","Over Budget") -> Within Budget
B10: Bricks | C10: Nos | D10: 620000 | E10: 498000 | F10: =D10-E10 -> 122000 | G10: =IF(E10<=D10,"Within Budget","Over Budget") -> Within Budget
B14: Purchase Price Variance — Cement & Steel
B15: PPV = (Standard Rate − Actual Rate) × Actual Qty. Positive = favourable, negative = adverse.
B16: Material | C16: Unit | D16: Std Rate (₹) | E16: Actual Rate (₹) | F16: Actual Qty | G16: Rate Diff (₹) | H16: Purchase Price Variance (₹) | I16: Result
B17: Cement | C17: Bag | D17: 380 | E17: 402 | F17: 33200 | G17: =D17-E17 -> -22 | H17: =(D17-E17)*F17 -> -730400 | I17: =IF(H17>=0,"Favourable","Adverse") -> Adverse
B18: Steel (TMT) | C18: kg | D18: 62 | E18: 58 | F18: 1058000 | G18: =D18-E18 -> 4 | H18: =(D18-E18)*F18 -> 4232000 | I18: =IF(H18>=0,"Favourable","Adverse") -> Favourable
B19: TOTAL PPV | H19: =SUM(H17:H18) -> 3501600 | I19: =IF(H19>=0,"Favourable","Adverse") -> Favourable

Sheet Cashflow
B2: Project Cash Flow — Inflow vs Outflow
B3: Inflow = receipts from RA bills. Outflow = payments (material, labour, subcontractor).
B5: Month | C5: Inflow (₹) | D5: Outflow (₹) | E5: Net (₹) | F5: Cumulative Net (₹)
B6: May-24 | C6: 11200000 | D6: 9500000 | E6: =C6-D6 -> 1700000 | F6: =E6 -> 1700000
B7: Jul-24 | C7: 13400000 | D7: 12800000 | E7: =C7-D7 -> 600000 | F7: =F6+E7 -> 2300000
B8: Sep-24 | C8: 14600000 | D8: 14600000 | E8: =C8-D8 -> 0 | F8: =F7+E8 -> 2300000
B9: Nov-24 | C9: 13600000 | D9: 13900000 | E9: =C9-D9 -> -300000 | F9: =F8+E9 -> 2000000
B10: Jan-25 | C10: 15700000 | D10: 15200000 | E10: =C10-D10 -> 500000 | F10: =F9+E10 -> 2500000
B11: Mar-25 | C11: 12300000 | D11: 14100000 | E11: =C11-D11 -> -1800000 | F11: =F10+E11 -> 700000
B12: May-25 | C12: 13900000 | D12: 13700000 | E12: =C12-D12 -> 200000 | F12: =F11+E12 -> 900000
B13: Jul-25 | C13: 11800000 | D13: 13400000 | E13: =C13-D13 -> -1600000 | F13: =F12+E13 -> -700000
B14: Sep-25 | C14: 7600000 | D14: 11200000 | E14: =C14-D14 -> -3600000 | F14: =F13+E14 -> -4300000
B15: TOTAL | C15: =SUM(C6:C14) -> 114100000 | D15: =SUM(D6:D14) -> 118400000 | E15: =SUM(E6:E14) -> -4300000
B18: Accrued Cost vs Cash Outflow — Reconciliation
B19: Accounting (accrued) cost and cash paid differ by movement in payables/accruals.
B20: Accrued Cost to Date (P&L, Project_Data) | D20: =Project_Data!D20 -> 122600000
B21: Total Cash Outflow (this sheet) | D21: =D15 -> 118400000
B22: Difference = Closing Payables / Accruals | D22: =D20-D21 -> 4200000

Sheet Milestones
B2: Milestone / Schedule Tracker
B4: Stage | C4: Planned % | D4: Actual % | E4: Variance (pts) | F4: Status
B5: Site Prep & Excavation | C5: 1 | D5: 1 | E5: =(D5-C5)*100 -> 0 | F5: =IF(D5>=C5,"On Track","Behind") -> On Track
B6: Foundation & Piling | C6: 1 | D6: 1 | E6: =(D6-C6)*100 -> 0 | F6: =IF(D6>=C6,"On Track","Behind") -> On Track
B7: Structural Frame | C7: 0.95 | D7: 0.92 | E7: =(D7-C7)*100 -> -3 | F7: =IF(D7>=C7,"On Track","Behind") -> Behind
B8: Masonry & Blockwork | C8: 0.85 | D8: 0.8 | E8: =(D8-C8)*100 -> -5 | F8: =IF(D8>=C8,"On Track","Behind") -> Behind
B9: MEP (Elec/Plumb) | C9: 0.7 | D9: 0.62 | E9: =(D9-C9)*100 -> -8 | F9: =IF(D9>=C9,"On Track","Behind") -> Behind
B10: Plastering & Flooring | C10: 0.55 | D10: 0.48 | E10: =(D10-C10)*100 -> -7 | F10: =IF(D10>=C10,"On Track","Behind") -> Behind
B11: Finishing & Interiors | C11: 0.3 | D11: 0.22 | E11: =(D11-C11)*100 -> -8 | F11: =IF(D11>=C11,"On Track","Behind") -> Behind
B12: External & Handover | C12: 0.1 | D12: 0.05 | E12: =(D12-C12)*100 -> -5 | F12: =IF(D12>=C12,"On Track","Behind") -> Behind
